flask_quickstart_generator/__init__.py
flask_quickstart_generator/cli.py
flask_quickstart_generator/cmd_handler.py
flask_quickstart_generator/css.py
flask_quickstart_generator/env.py
flask_quickstart_generator/forms.py
flask_quickstart_generator/html.py
flask_quickstart_generator/js.py
flask_quickstart_generator/main.py
flask_quickstart_generator/model.py
flask_quickstart_generator/routes_.py
flask_quickstart_generator/settings.py
flask_quickstart_generator-1.1.3.dist-info/LICENSE.txt
flask_quickstart_generator-1.1.3.dist-info/METADATA
flask_quickstart_generator-1.1.3.dist-info/WHEEL
flask_quickstart_generator-1.1.3.dist-info/entry_points.txt
flask_quickstart_generator-1.1.3.dist-info/top_level.txt
flask_quickstart_generator-1.1.3.dist-info/RECORD
