Metadata-Version: 2.2
Name: flask_quickstart_generator
Version: 1.1.3
Summary: Flask Quickstart Generator streamlines Flask development by automatically generating a structured folder layout, expediting project setup.
Home-page: https://ktecht.pythonanywhere.com/
Author: Kennartech
Author-email: kennartdev@gmail.com
Maintainer: Kennartech.Dev
Maintainer-email: kennartdev@gmail.com
License: MIT
Classifier: Programming Language :: Python
Classifier: Programming Language :: Python :: 3
Classifier: Programming Language :: Python :: 3.10
Classifier: Programming Language :: Python :: 3.11
Classifier: Programming Language :: Python :: 3.12
Classifier: Programming Language :: Python :: 3.13
License-File: LICENSE.txt
Requires-Dist: Flask
Requires-Dist: WTForms
Requires-Dist: pillow
Requires-Dist: psycopg2
Requires-Dist: waitress
Requires-Dist: Flask-WTF
Requires-Dist: Flask-Login
Requires-Dist: flask-babel
Requires-Dist: Flask-Login
Requires-Dist: Flask-Bcrypt
Requires-Dist: python-dotenv
Requires-Dist: Flask-Caching
Requires-Dist: Flask-Limiter
Requires-Dist: python-dotenv
Requires-Dist: Flask-Migrate
Requires-Dist: Flask-Session
Requires-Dist: Flask-SQLAlchemy
Dynamic: author
Dynamic: author-email
Dynamic: classifier
Dynamic: description
Dynamic: description-content-type
Dynamic: home-page
Dynamic: license
Dynamic: maintainer
Dynamic: maintainer-email
Dynamic: requires-dist
Dynamic: summary
